odoo/addons/calendar_event_multi_company/README.rst
odoo/addons/calendar_event_multi_company/__init__.py
odoo/addons/calendar_event_multi_company/__manifest__.py
odoo/addons/calendar_event_multi_company/i18n/calendar_event_multi_company.pot
odoo/addons/calendar_event_multi_company/i18n/it.po
odoo/addons/calendar_event_multi_company/models/__init__.py
odoo/addons/calendar_event_multi_company/models/calendar_event.py
odoo/addons/calendar_event_multi_company/readme/CONTRIBUTORS.rst
odoo/addons/calendar_event_multi_company/readme/DESCRIPTION.rst
odoo/addons/calendar_event_multi_company/security/calendar_event.xml
odoo/addons/calendar_event_multi_company/static/description/icon.png
odoo/addons/calendar_event_multi_company/static/description/index.html
odoo/addons/calendar_event_multi_company/views/calendar_event.xml
odoo12_addon_calendar_event_multi_company-12.0.1.0.0.99.dev7.dist-info/METADATA
odoo12_addon_calendar_event_multi_company-12.0.1.0.0.99.dev7.dist-info/WHEEL
odoo12_addon_calendar_event_multi_company-12.0.1.0.0.99.dev7.dist-info/top_level.txt
odoo12_addon_calendar_event_multi_company-12.0.1.0.0.99.dev7.dist-info/RECORD
